livepy/__init__.py
livepy-0.0.1.dist-info/LICENSE
livepy-0.0.1.dist-info/METADATA
livepy-0.0.1.dist-info/WHEEL
livepy-0.0.1.dist-info/top_level.txt
livepy-0.0.1.dist-info/RECORD
