Metadata-Version: 2.1
Name: livepy
Version: 0.0.1
Summary: A live python shell to run code online.
Home-page: https://github.com/prshnt19/LivePy
Author: Prashant Rawat
Author-email: prashant.rawat216@gmail.com
License: UNKNOWN
Platform: UNKNOWN
Classifier: Programming Language :: Python :: 3
Classifier: License :: OSI Approved :: MIT License
Classifier: Operating System :: OS Independent
Requires-Python: >=3.6
